magnetsting/__init__.py
magnetsting/magnetsting.py
magnetsting-1.0.8.dist-info/LICENSE
magnetsting-1.0.8.dist-info/METADATA
magnetsting-1.0.8.dist-info/WHEEL
magnetsting-1.0.8.dist-info/top_level.txt
magnetsting-1.0.8.dist-info/RECORD
