Metadata-Version: 2.1
Name: magnetsting
Version: 1.0.8
Summary: Create command-line projects with ease.
Author: DarkMatter
License: GNU GENERAL PUBLIC LICENSE
Project-URL: Homepage, https://github.com/darkmattergit/magnetsting
Project-URL: Bug Tracker, https://github.com/darkmattergit/magnetsting/issues
Keywords: command-line,cli,framework
Classifier: Development Status :: 5 - Production/Stable
Classifier: License :: OSI Approved :: GNU General Public License v3 (GPLv3)
Classifier: Operating System :: POSIX :: Linux
Classifier: Topic :: Software Development :: Libraries :: Python Modules
Requires-Python: >=3.8
License-File: LICENSE
